yaf/__init__.py
yaf/yaf.py
yaf-0.0.1.dist-info/METADATA
yaf-0.0.1.dist-info/WHEEL
yaf-0.0.1.dist-info/top_level.txt
yaf-0.0.1.dist-info/RECORD
